tidml/__init__.py
tidml/algorithm.py
tidml/data_source.py
tidml/engine.py
tidml/model_persistor.py
tidml/preparator.py
tidml/serving.py
tidml/utils.py
tidml-0.1.4.dist-info/DESCRIPTION.rst
tidml-0.1.4.dist-info/METADATA
tidml-0.1.4.dist-info/RECORD
tidml-0.1.4.dist-info/WHEEL
tidml-0.1.4.dist-info/metadata.json
tidml-0.1.4.dist-info/top_level.txt
