Metadata-Version: 2.0
Name: tidml
Version: 0.1.4
Summary: Telefónica I+D Machine Learning Workflow Framework
Home-page: https://github.com/tidchile/tidml
Author: Ricardo Stuven
Author-email: ricardo.stuven@telefonica.com
License: UNKNOWN
Download-URL: https://github.com/tidchile/tidml/tarball/0.1.4
Platform: UNKNOWN
